post_scene/BuiltFunction.py
post_scene/Xmind2Yaml.py
post_scene/__init__.py
post_scene/creator.py
post_scene/models.py
post_scene/parser.py
post_scene/post_scene.py
post_scene/yaml2Xmind.py
PostScene-0.8.2.dist-info/LICENSE
PostScene-0.8.2.dist-info/METADATA
PostScene-0.8.2.dist-info/WHEEL
PostScene-0.8.2.dist-info/top_level.txt
PostScene-0.8.2.dist-info/RECORD
