Metadata-Version: 2.1
Name: PostScene
Version: 0.8.2
Summary: 一个强大的工具，基于 Postman 接口自动化场景设计
Home-page: https://gitee.com/tangyajun/PostScene
Author: cheryl tong
Author-email: cheryl_98750@163.com
License: GNU Affero General Public License v3 
Keywords: scene,postman,automation,testing,api
Platform: UNKNOWN
Classifier: Operating System :: OS Independent
Classifier: License :: OSI Approved :: GNU Affero General Public License v3 
Classifier: Programming Language :: Python :: 3.7
Requires-Python: >=3.7.0
Requires-Dist: ruamel.yaml (==0.16.10)
Requires-Dist: ruamel.yaml.clib (==0.2.0)
Requires-Dist: XMind (==1.2.0)
